jupyterlab_esl37/__init__.py
jupyterlab_esl37/_version.py
jupyterlab_esl37-0.0.3.data/data/share/jupyter/labextensions/jupyterlab-esl37/package.json
jupyterlab_esl37-0.0.3.data/data/share/jupyter/labextensions/jupyterlab-esl37/schemas/jupyterlab-esl37/package.json.orig
jupyterlab_esl37-0.0.3.data/data/share/jupyter/labextensions/jupyterlab-esl37/schemas/jupyterlab-esl37/plugin.json
jupyterlab_esl37-0.0.3.data/data/share/jupyter/labextensions/jupyterlab-esl37/static/184.c78acc3bea5da268dc98.js
jupyterlab_esl37-0.0.3.data/data/share/jupyter/labextensions/jupyterlab-esl37/static/421.a28879aa9daad3686566.js
jupyterlab_esl37-0.0.3.data/data/share/jupyter/labextensions/jupyterlab-esl37/static/728.7c5beb779e5ff2a8727a.js
jupyterlab_esl37-0.0.3.data/data/share/jupyter/labextensions/jupyterlab-esl37/static/remoteEntry.5fc868a82b94eab58a1b.js
jupyterlab_esl37-0.0.3.data/data/share/jupyter/labextensions/jupyterlab-esl37/static/style.js
jupyterlab_esl37-0.0.3.data/data/share/jupyter/labextensions/jupyterlab-esl37/static/third-party-licenses.json
jupyterlab_esl37-0.0.3.data/data/share/jupyter/labextensions/jupyterlab-esl37/install.json
jupyterlab_esl37-0.0.3.dist-info/METADATA
jupyterlab_esl37-0.0.3.dist-info/WHEEL
jupyterlab_esl37-0.0.3.dist-info/licenses/LICENSE
jupyterlab_esl37-0.0.3.dist-info/RECORD
