Metadata-Version: 2.3
Name: jupyterlab_esl37
Version: 0.0.3
Dynamic: Keywords
Summary: ESL37 support for Jupyter Lab.
Project-URL: Homepage, https://github.com/nssac/jupyterlab-esl37
Project-URL: Bug Tracker, https://github.com/nssac/jupyterlab-esl37/issues
Project-URL: Repository, https://github.com/nssac/jupyterlab-esl37.git
Author-email: Parantapa Bhattacharya <pb@parantapa.net>
License: Copyright (C) 2024 Rector and Visitors of the University of Virginia
License-File: LICENSE
Classifier: Framework :: Jupyter
Classifier: Framework :: Jupyter :: JupyterLab
Classifier: Framework :: Jupyter :: JupyterLab :: 4
Classifier: Framework :: Jupyter :: JupyterLab :: Extensions
Classifier: Framework :: Jupyter :: JupyterLab :: Extensions :: Prebuilt
Classifier: License :: OSI Approved :: BSD License
Classifier: Programming Language :: Python
Classifier: Programming Language :: Python :: 3
Classifier: Programming Language :: Python :: 3.8
Classifier: Programming Language :: Python :: 3.9
Classifier: Programming Language :: Python :: 3.10
Classifier: Programming Language :: Python :: 3.11
Classifier: Programming Language :: Python :: 3.12
Requires-Python: >=3.8
